simp_hint/__init__.py
simp_hint/tensor_type_hints.py
simp_hint-0.0.2.dist-info/METADATA
simp_hint-0.0.2.dist-info/WHEEL
simp_hint-0.0.2.dist-info/top_level.txt
simp_hint-0.0.2.dist-info/RECORD
